{
  "p2p": {
    "name": "node9",
    "bindAddress": "127.0.0.9",
    "upnp": false,
    "upnpGatewayTimeout": 7000,
    "upnpDiscoverTimeout": 3000,
    "port": 9089,
    "knownPeers": [
      "127.0.0.1:9081",
      "127.0.0.2:9082"
    ],
    "addedMaxDelay": 500,
    "maxConnections": 10
  },
  "walletSeed": "genesis-9",
  "walletDir": "/tmp/bifrost/data9/wallet",
  "keyFileDir": "keyfiles/node9",
  "dataDir": "/tmp/bifrost/data9/blockchain",
  "sbrDir": "/tmp/bifrost/data9/sbr",
  "logDir": "/tmp/bifrost/data9/log",
  "rpcPort": 9099,
  "rpcAllowed": [],
  "maxRollback": 100,
  "offlineGeneration": true,
  "blockGenerationDelay": 5000,
  "targetBlockTime": 30000,
  "cors": false,
  "agent": "test-net9",
  "testnet": true,
  "version": [3, 0, 0],
  "forkHeight": 0
}
